inflecteur/__init__.py
inflecteur-0.1.4.dist-info/LICENSE
inflecteur-0.1.4.dist-info/METADATA
inflecteur-0.1.4.dist-info/WHEEL
inflecteur-0.1.4.dist-info/top_level.txt
inflecteur-0.1.4.dist-info/RECORD
