Metadata-Version: 2.1
Name: inflecteur
Version: 0.1.4
Summary: python inflector for French language : control gender, tense and number
Home-page: https://github.com/Achuttarsing/inflecteur
Author: Adrien Chuttarsing
Author-email: adrien.chuttarsing@gmail.com
License: MIT
Keywords: nlp inflector python inflecteur data augmentation french
Platform: UNKNOWN
Classifier: Natural Language :: French
Classifier: Intended Audience :: Developers
Classifier: Intended Audience :: Education
Classifier: Intended Audience :: Science/Research
Classifier: Operating System :: OS Independent
Classifier: Programming Language :: Python :: 3
Classifier: Programming Language :: Python :: 3.6
Classifier: Programming Language :: Python :: 3.7
Classifier: Topic :: Scientific/Engineering :: Artificial Intelligence
Classifier: Topic :: Text Processing :: Linguistic
Requires-Dist: sacremoses
Requires-Dist: tokenizers
Requires-Dist: sentencepiece
Requires-Dist: transformers
Requires-Dist: pandas
Requires-Dist: numpy
